sashay/__init__.py
sashay/__main__.py
sashay/main.py
sashay/menu.py
sashay/outlook.py
sashay/system.py
sashay/assets/cat.json
sashay/assets/data.json
sashay-2022.4.dist-info/LICENSE
sashay-2022.4.dist-info/METADATA
sashay-2022.4.dist-info/WHEEL
sashay-2022.4.dist-info/entry_points.txt
sashay-2022.4.dist-info/top_level.txt
sashay-2022.4.dist-info/RECORD
