Metadata-Version: 2.1
Name: sashay
Version: 2022.4
Summary: All in one automatic installer for useful tools
Home-page: https://github.com/scalabli/sashay
Author: Gerrishon Sirere
Author-email: scalabli@pm.me
Maintainer: Scalabli.
Maintainer-email: scalabli@pm.me
License: MIT
Project-URL: Donate, https://ko-fi.com/scalabli
Project-URL: Documentation, https://github.com/scalabli/sashay
Project-URL: Changes, https://github.com/scalabli/sashay
Project-URL: Source Code, https://github.com/scalabli/sashay
Project-URL: Issue Tracker, https://github.com/scalabli/sashay/issues/
Project-URL: Twitter, https://twitter.com/scalabli
Project-URL: Chat, https://gitter.im/scalabli
Platform: UNKNOWN
Classifier: Development Status :: 5 - Production/Stable
Classifier: Intended Audience :: Developers
Classifier: Environment :: Console
Classifier: License :: OSI Approved :: MIT License
Classifier: Operating System :: OS Independent
Classifier: Programming Language :: Python :: 3.8
Classifier: Programming Language :: Python :: 3.9
Classifier: Programming Language :: Python :: 3.10
Requires-Python: >=3.8
License-File: LICENSE
Requires-Dist: quo (>=2022.5)
